[
    {
        "title": "Gold Coast trip 2024",
        "_tasks": [
            {
                "title": "Carry-on",
                "description": "Description goes here",
                "dueDate": "2019",
                "priority": 0,
                "id": 0,
                "_steps": [
                    {
                        "id": 0,
                        "title": "Laptop",
                        "completed": false
                    },
                    {
                        "id": 1,
                        "title": "Hoodie",
                        "completed": true
                    },
                    {
                        "id": 2,
                        "title": "Airpods",
                        "completed": false
                    },
                    {
                        "id": 3,
                        "title": "Housekeys",
                        "completed": false
                    }
                ],
                "_stepsGenerated": 4,
                "HTMLroot": {},
                "stepsRoot": {}
            },
            {
                "title": "Clothing",
                "description": "Description goes here",
                "dueDate": "1984",
                "priority": 0,
                "id": 0,
                "_steps": [
                    {
                        "id": 0,
                        "title": "Shirts x 4",
                        "completed": true
                    },
                    {
                        "id": 1,
                        "title": "Socks x 4",
                        "completed": false
                    },
                    {
                        "id": 2,
                        "title": "Undies x 4",
                        "completed": false
                    },
                    {
                        "id": 3,
                        "title": "Jeans x 1",
                        "completed": false
                    },
                    {
                        "id": 4,
                        "title": "Winter jacket x 1",
                        "completed": false
                    }
                ],
                "_stepsGenerated": 5,
                "HTMLroot": {},
                "stepsRoot": {}
            },
            {
                "title": "Beach",
                "description": "",
                "dueDate": "",
                "priority": 0,
                "id": 0,
                "_steps": [
                    {
                        "id": 0,
                        "title": "Swimmers",
                        "completed": false
                    },
                    {
                        "id": 1,
                        "title": "Swim goggles",
                        "completed": false
                    },
                    {
                        "id": 2,
                        "title": "Mesh bag",
                        "completed": false
                    },
                    {
                        "id": 3,
                        "title": "Sports band for watch",
                        "completed": false
                    }
                ],
                "_stepsGenerated": 4,
                "HTMLroot": {},
                "stepsRoot": {}
            },
            {
                "title": "Bathroom",
                "description": "",
                "dueDate": "",
                "priority": 0,
                "id": 0,
                "_steps": [
                    {
                        "id": 0,
                        "title": "Toothbrush",
                        "completed": false
                    },
                    {
                        "id": 1,
                        "title": "Toothpaste",
                        "completed": false
                    },
                    {
                        "id": 2,
                        "title": "Floss",
                        "completed": false
                    },
                    {
                        "id": 3,
                        "title": "Sunscreen",
                        "completed": false
                    },
                    {
                        "id": 4,
                        "title": "Cotton buds",
                        "completed": false
                    },
                    {
                        "id": 5,
                        "title": "Reading glasses",
                        "completed": false
                    },
                    {
                        "id": 6,
                        "title": "Paracetamol",
                        "completed": false
                    }
                ],
                "_stepsGenerated": 7,
                "HTMLroot": {},
                "stepsRoot": {}
            },
            {
                "title": "Tech",
                "description": "",
                "dueDate": "",
                "priority": 0,
                "id": 0,
                "_steps": [
                    {
                        "id": 0,
                        "title": "AC wall plug",
                        "completed": false
                    },
                    {
                        "id": 1,
                        "title": "usbc cable",
                        "completed": false
                    },
                    {
                        "id": 2,
                        "title": "phone charging stand",
                        "completed": false
                    },
                    {
                        "id": 3,
                        "title": "watch charger",
                        "completed": false
                    },
                    {
                        "id": 4,
                        "title": "Nintendo Switch",
                        "completed": false
                    }
                ],
                "_stepsGenerated": 5,
                "HTMLroot": {},
                "stepsRoot": {}
            }
        ],
        "id": 0
    },
    {
        "title": "Groceries",
        "_tasks": [
            {
                "title": "Minestrone",
                "description": "Description goes here",
                "dueDate": "2019",
                "priority": 0,
                "id": 0,
                "_steps": [
                    {
                        "id": 0,
                        "title": "celery",
                        "completed": false
                    },
                    {
                        "id": 1,
                        "title": "2 carrots",
                        "completed": false
                    },
                    {
                        "id": 2,
                        "title": "baby spinach",
                        "completed": false
                    },
                    {
                        "id": 3,
                        "title": "1 onion",
                        "completed": false
                    },
                    {
                        "id": 4,
                        "title": "garlic",
                        "completed": false
                    },
                    {
                        "id": 5,
                        "title": "1 zucchini",
                        "completed": false
                    },
                    {
                        "id": 6,
                        "title": "",
                        "completed": false
                    },
                    {
                        "id": 7,
                        "title": "",
                        "completed": false
                    },
                    {
                        "id": 8,
                        "title": "",
                        "completed": false
                    },
                    {
                        "id": 9,
                        "title": "",
                        "completed": false
                    },
                    {
                        "id": 10,
                        "title": "",
                        "completed": false
                    },
                    {
                        "id": 11,
                        "title": "",
                        "completed": false
                    },
                    {
                        "id": 12,
                        "title": "",
                        "completed": false
                    }
                ],
                "_stepsGenerated": 13,
                "HTMLroot": {},
                "stepsRoot": {}
            },
            {
                "title": "NEW TASK",
                "description": "",
                "dueDate": "",
                "priority": "",
                "id": 0,
                "_steps": [
                    {
                        "id": 0,
                        "title": "",
                        "completed": false
                    },
                    {
                        "id": 1,
                        "title": "",
                        "completed": false
                    },
                    {
                        "id": 2,
                        "title": "",
                        "completed": false
                    },
                    {
                        "id": 3,
                        "title": "",
                        "completed": false
                    },
                    {
                        "id": 4,
                        "title": "",
                        "completed": false
                    },
                    {
                        "id": 5,
                        "title": "",
                        "completed": false
                    }
                ],
                "_stepsGenerated": 6,
                "HTMLroot": {},
                "stepsRoot": {}
            }
        ],
        "id": 1
    }
]